taiwan_holidays/__init__.py
taiwan_holidays/taiwan_calendar.py
taiwan_holidays/data/108年中華民國政府行政機關辦公日曆表.csv
taiwan_holidays/data/109年中華民國政府行政機關辦公日曆表.csv
taiwan_holidays/data/111年中華民國政府行政機關辦公日曆表.csv
taiwan_holidays/data/112年中華民國政府行政機關辦公日曆表.csv
taiwan_holidays/data/113年中華民國政府行政機關辦公日曆表.csv
taiwan_holidays/data/114年中華民國政府行政機關辦公日曆表.csv
taiwan_holidays/data/115年中華民國政府行政機關辦公日曆表.csv
taiwan_holidays-0.2026.2.dist-info/METADATA
taiwan_holidays-0.2026.2.dist-info/WHEEL
taiwan_holidays-0.2026.2.dist-info/licenses/LICENSE
taiwan_holidays-0.2026.2.dist-info/RECORD
