Metadata-Version: 2.4
Name: taiwan-holidays
Version: 0.2026.2
Summary: A Python package for determining whether a given date is a workday or a holiday in Taiwan, based on the official administrative calendar.
Project-URL: homepage, https://github.com/Chesham/taiwan-holidays
Project-URL: repository, https://github.com/Chesham/taiwan-holidays
Project-URL: documentation, https://github.com/Chesham/taiwan-holidays
Author-email: chesham <c.moweb@gmail.com>
License: The MIT License (MIT)
License-File: LICENSE
Classifier: Intended Audience :: Developers
Classifier: License :: OSI Approved :: MIT License
Classifier: Operating System :: OS Independent
Classifier: Programming Language :: Python :: 3
Classifier: Programming Language :: Python :: 3.9
Classifier: Programming Language :: Python :: 3.10
Classifier: Programming Language :: Python :: 3.11
Classifier: Programming Language :: Python :: 3.12
Classifier: Programming Language :: Python :: 3.13
Classifier: Topic :: Software Development :: Libraries
Classifier: Topic :: Software Development :: Libraries :: Python Modules
Requires-Python: >=3.9
Requires-Dist: pandas==2.2.3
Requires-Dist: python-dateutil==2.9.0.post0
